fgdata/__init__.py
fgdata/futures/__init__.py
fgdata/futures/future_news.py
test/__init__.py
test/futures/__init__.py
test/futures/test_future_news.py
fgdata-0.1.1.dist-info/METADATA
fgdata-0.1.1.dist-info/WHEEL
fgdata-0.1.1.dist-info/top_level.txt
fgdata-0.1.1.dist-info/RECORD
