Metadata-Version: 2.1
Name: fgdata
Version: 0.1.1
Summary: A data toolkit for the Chinese futures market.
Home-page: https://github.com/shuzip/fgdata
Author: shuzip
License: MIT
Keywords: futures,fund,finance,data
Classifier: Programming Language :: Python :: 3
Classifier: License :: OSI Approved :: MIT License
Classifier: Operating System :: OS Independent
Requires-Python: >=3.8
Requires-Dist: requests
Requires-Dist: pandas
Requires-Dist: lxml
